{
  "/api/send-mail/route": "app/api/send-mail/route.js",
  "/_not-found/page": "app/_not-found/page.js",
  "/eng/about-me/page": "app/eng/about-me/page.js",
  "/eng/page": "app/eng/page.js",
  "/impressum/page": "app/impressum/page.js",
  "/eng/web-development/page": "app/eng/web-development/page.js",
  "/eng/contact/page": "app/eng/contact/page.js",
  "/kontakt/page": "app/kontakt/page.js",
  "/eng/teaching/page": "app/eng/teaching/page.js",
  "/page": "app/page.js",
  "/eng/programming/page": "app/eng/programming/page.js",
  "/programmierung/page": "app/programmierung/page.js",
  "/lehre/page": "app/lehre/page.js",
  "/projekte/wortwahl/page": "app/projekte/wortwahl/page.js",
  "/ueber_mich/page": "app/ueber_mich/page.js",
  "/wortwahl/page": "app/wortwahl/page.js",
  "/webentwicklung/page": "app/webentwicklung/page.js"
}